[
  {
    "title": "Naruto Shippuden",
    "globalEpisodeNumber": 139,
    "sizeInMB": 82.74,
    "seasonEpisodeNumber": 27,
    "downloadUrl": "https://eng.cartoonsarea.cc/USER-DATA/Cartoonsarea/English/N/Naruto%20Shippuden/Season%206/Episode%20139//139%20The%20Mystery%20of%20Tobi.mp4",
    "fileName": "The Mystery of Tobi.mp4",
    "s3Path": "tv/Naruto Shippuden (2009)/Season 06/S06E27 - (Ep139) The Mystery of Tobi.mp4",
    "index": 1693
  },
  {
    "title": "The Legend of Korra",
    "globalEpisodeNumber": 13,
    "sizeInMB": 82.75,
    "seasonEpisodeNumber": 1,
    "downloadUrl": "https://eng.cartoonsarea.cc/USER-DATA/Cartoonsarea/English/A/Avatar%20The%20Legend%20of%20Korra/Season%202%20Spirits/Episode%2013//13%20Rebel%20Spirit.mp4",
    "fileName": "Rebel Spirit.mp4",
    "s3Path": "tv/The Legend of Korra (2012)/Season 02/S02E01 - (Ep13) Rebel Spirit.mp4",
    "index": 1694
  },
  {
    "title": "Naruto",
    "globalEpisodeNumber": 30,
    "sizeInMB": 82.75,
    "seasonEpisodeNumber": 30,
    "downloadUrl": "https://eng.cartoonsarea.cc/USER-DATA/Cartoonsarea/English/N/Naruto/Season%201/Episode%2030//30%20The%20Sharingan%20Revived,%20Dragon%20Flame%20Jutsu.mp4",
    "fileName": "The Sharingan Revived, Dragon Flame Jutsu.mp4",
    "s3Path": "tv/Naruto (2005)/Season 01/S01E30 - (Ep30) The Sharingan Revived, Dragon Flame Jutsu.mp4",
    "index": 1695
  },
  {
    "title": "Naruto",
    "globalEpisodeNumber": 35,
    "sizeInMB": 82.75,
    "seasonEpisodeNumber": 35,
    "downloadUrl": "https://eng.cartoonsarea.cc/USER-DATA/Cartoonsarea/English/N/Naruto/Season%201/Episode%2035//35%20The%20Scroll's%20Secret.mp4",
    "fileName": "The Scroll's Secret.mp4",
    "s3Path": "tv/Naruto (2005)/Season 01/S01E35 - (Ep35) The Scroll's Secret.mp4",
    "index": 1696
  },
  {
    "title": "Naruto Shippuden",
    "globalEpisodeNumber": 228,
    "sizeInMB": 82.75,
    "seasonEpisodeNumber": 7,
    "downloadUrl": "https://eng.cartoonsarea.cc/USER-DATA/Cartoonsarea/English/N/Naruto%20Shippuden/Season%2011/Episode%20228//228%20Fight!%20Rock%20Lee!.mp4",
    "fileName": "Fight! Rock Lee!.mp4",
    "s3Path": "tv/Naruto Shippuden (2009)/Season 11/S11E07 - (Ep228) Fight! Rock Lee!.mp4",
    "index": 1697
  },
  {
    "title": "Naruto Shippuden",
    "globalEpisodeNumber": 305,
    "sizeInMB": 82.75,
    "seasonEpisodeNumber": 10,
    "downloadUrl": "https://eng.cartoonsarea.cc/USER-DATA/Cartoonsarea/English/N/Naruto%20Shippuden/Season%2014/Episode%20305//305%20The%20Vengeful.mp4",
    "fileName": "The Vengeful.mp4",
    "s3Path": "tv/Naruto Shippuden (2009)/Season 14/S14E10 - (Ep305) The Vengeful.mp4",
    "index": 1698
  },
  {
    "title": "Naruto",
    "globalEpisodeNumber": 73,
    "sizeInMB": 82.76,
    "seasonEpisodeNumber": 38,
    "downloadUrl": "https://eng.cartoonsarea.cc/USER-DATA/Cartoonsarea/English/N/Naruto/Season%202/Episode%2072//72%20A%20Mistake%20From%20The%20Past,%20A%20Face%20Revealed!.mp4",
    "fileName": "A Mistake From The Past, A Face Revealed!.mp4",
    "s3Path": "tv/Naruto (2005)/Season 02/S02E38 - (Ep73) A Mistake From The Past, A Face Revealed!.mp4",
    "index": 1699
  },
  {
    "title": "Naruto",
    "globalEpisodeNumber": 139,
    "sizeInMB": 82.76,
    "seasonEpisodeNumber": 8,
    "downloadUrl": "https://eng.cartoonsarea.cc/USER-DATA/Cartoonsarea/English/N/Naruto/Season%204/Episode%20139//139%20Pure%20Terror!%20The%20House%20Of%20Orochimaru!.mp4",
    "fileName": "Pure Terror! The House Of Orochimaru!.mp4",
    "s3Path": "tv/Naruto (2005)/Season 04/S04E08 - (Ep139) Pure Terror! The House Of Orochimaru!.mp4",
    "index": 1700
  },
  {
    "title": "Naruto Shippuden",
    "globalEpisodeNumber": 413,
    "sizeInMB": 82.76,
    "seasonEpisodeNumber": 20,
    "downloadUrl": "https://eng.cartoonsarea.cc/USER-DATA/Cartoonsarea/English/N/Naruto%20Shippuden/Season%2019/Episode%20413//413%20Hopes%20Entrusted%20to%20the%20Future.mp4",
    "fileName": "Hopes Entrusted to the Future.mp4",
    "s3Path": "tv/Naruto Shippuden (2009)/Season 19/S19E20 - (Ep413) Hopes Entrusted to the Future.mp4",
    "index": 1701
  },
  {
    "title": "Naruto Shippuden",
    "globalEpisodeNumber": 425,
    "sizeInMB": 82.76,
    "seasonEpisodeNumber": 12,
    "downloadUrl": "https://eng.cartoonsarea.cc/USER-DATA/Cartoonsarea/English/N/Naruto%20Shippuden/Season%2020/Episode%20425//425%20The%20Infinite%20Dream.mp4",
    "fileName": "The Infinite Dream.mp4",
    "s3Path": "tv/Naruto Shippuden (2009)/Season 20/S20E12 - (Ep425) The Infinite Dream.mp4",
    "index": 1702
  },
  {
    "title": "Naruto",
    "globalEpisodeNumber": 69,
    "sizeInMB": 82.77,
    "seasonEpisodeNumber": 34,
    "downloadUrl": "https://eng.cartoonsarea.cc/USER-DATA/Cartoonsarea/English/N/Naruto/Season%202/Episode%2069//69%20Village%20In%20Distress,%20A%20New%20A-Ranked%20Mission!.mp4",
    "fileName": "Village In Distress, A New A-Ranked Mission!.mp4",
    "s3Path": "tv/Naruto (2005)/Season 02/S02E34 - (Ep69) Village In Distress, A New A-Ranked Mission!.mp4",
    "index": 1703
  },
  {
    "title": "Naruto",
    "globalEpisodeNumber": 85,
    "sizeInMB": 82.77,
    "seasonEpisodeNumber": 2,
    "downloadUrl": "https://eng.cartoonsarea.cc/USER-DATA/Cartoonsarea/English/N/Naruto/Season%203/Episode%2085//85%20Hate%20Among%20The%20Uchihas,%20The%20Last%20Of%20The%20Clan!.mp4",
    "fileName": "Hate Among The Uchihas, The Last Of The Clan!.mp4",
    "s3Path": "tv/Naruto (2005)/Season 03/S03E02 - (Ep85) Hate Among The Uchihas, The Last Of The Clan!.mp4",
    "index": 1704
  },
  {
    "title": "Naruto Shippuden",
    "globalEpisodeNumber": 330,
    "sizeInMB": 82.78,
    "seasonEpisodeNumber": 10,
    "downloadUrl": "https://eng.cartoonsarea.cc/USER-DATA/Cartoonsarea/English/N/Naruto%20Shippuden/Season%2015/Episode%20330//330%20The%20Promise%20of%20Victory.mp4",
    "fileName": "The Promise of Victory.mp4",
    "s3Path": "tv/Naruto Shippuden (2009)/Season 15/S15E10 - (Ep330) The Promise of Victory.mp4",
    "index": 1705
  },
  {
    "title": "Naruto Shippuden",
    "globalEpisodeNumber": 169,
    "sizeInMB": 82.79,
    "seasonEpisodeNumber": 18,
    "downloadUrl": "https://eng.cartoonsarea.cc/USER-DATA/Cartoonsarea/English/N/Naruto%20Shippuden/Season%208/Episode%20169//169%20The%20Two%20Students.mp4",
    "fileName": "The Two Students.mp4",
    "s3Path": "tv/Naruto Shippuden (2009)/Season 08/S08E18 - (Ep169) The Two Students.mp4",
    "index": 1706
  },
  {
    "title": "Naruto Shippuden",
    "globalEpisodeNumber": 285,
    "sizeInMB": 82.8,
    "seasonEpisodeNumber": 10,
    "downloadUrl": "https://eng.cartoonsarea.cc/USER-DATA/Cartoonsarea/English/N/Naruto%20Shippuden/Season%2013/Episode%20285//285%20User%20of%20the%20Scorch%20Style%20Pakura%20of%20the%20Sand!.mp4",
    "fileName": "User of the Scorch Style Pakura of the Sand!.mp4",
    "s3Path": "tv/Naruto Shippuden (2009)/Season 13/S13E10 - (Ep285) User of the Scorch Style Pakura of the Sand!.mp4",
    "index": 1707
  },
  {
    "title": "Naruto Shippuden",
    "globalEpisodeNumber": 294,
    "sizeInMB": 82.8,
    "seasonEpisodeNumber": 19,
    "downloadUrl": "https://eng.cartoonsarea.cc/USER-DATA/Cartoonsarea/English/N/Naruto%20Shippuden/Season%2013/Episode%20294//294%20Power%20-%20Episode%205.mp4",
    "fileName": "Power - Episode 5.mp4",
    "s3Path": "tv/Naruto Shippuden (2009)/Season 13/S13E19 - (Ep294) Power - Episode 5.mp4",
    "index": 1708
  },
  {
    "title": "Naruto",
    "globalEpisodeNumber": 1,
    "sizeInMB": 82.81,
    "seasonEpisodeNumber": 1,
    "downloadUrl": "https://eng.cartoonsarea.cc/USER-DATA/Cartoonsarea/English/N/Naruto/Season%201/Episode%201//01%20Enter%20Naruto%20Uzumaki.mp4",
    "fileName": "Enter Naruto Uzumaki.mp4",
    "s3Path": "tv/Naruto (2005)/Season 01/S01E01 - (Ep01) Enter Naruto Uzumaki.mp4",
    "index": 1709
  },
  {
    "title": "Naruto",
    "globalEpisodeNumber": 181,
    "sizeInMB": 82.81,
    "seasonEpisodeNumber": 50,
    "downloadUrl": "https://eng.cartoonsarea.cc/USER-DATA/Cartoonsarea/English/N/Naruto/Season%204/Episode%20181//181%20Hoshikage,%20The%20Buried%20Truth.mp4",
    "fileName": "Hoshikage, The Buried Truth.mp4",
    "s3Path": "tv/Naruto (2005)/Season 04/S04E50 - (Ep181) Hoshikage, The Buried Truth.mp4",
    "index": 1710
  },
  {
    "title": "Naruto",
    "globalEpisodeNumber": 83,
    "sizeInMB": 82.82,
    "seasonEpisodeNumber": 48,
    "downloadUrl": "https://eng.cartoonsarea.cc/USER-DATA/Cartoonsarea/English/N/Naruto/Season%202/Episode%2083//83%20Jiraya,%20Naruto's%20Potential%20Disaster!.mp4",
    "fileName": "Jiraya, Naruto's Potential Disaster!.mp4",
    "s3Path": "tv/Naruto (2005)/Season 02/S02E48 - (Ep83) Jiraya, Naruto's Potential Disaster!.mp4",
    "index": 1711
  },
  {
    "title": "The Legend of Korra",
    "globalEpisodeNumber": 2,
    "sizeInMB": 82.84,
    "seasonEpisodeNumber": 2,
    "downloadUrl": "https://eng.cartoonsarea.cc/USER-DATA/Cartoonsarea/English/A/Avatar%20The%20Legend%20of%20Korra/Season%201%20Air/Episode%2002//02%20A%20Leaf%20in%20the%20Wind.mp4",
    "fileName": "A Leaf in the Wind.mp4",
    "s3Path": "tv/The Legend of Korra (2012)/Season 01/S01E02 - (Ep02) A Leaf in the Wind.mp4",
    "index": 1712
  },
  {
    "title": "Naruto",
    "globalEpisodeNumber": 27,
    "sizeInMB": 82.84,
    "seasonEpisodeNumber": 27,
    "downloadUrl": "https://eng.cartoonsarea.cc/USER-DATA/Cartoonsarea/English/N/Naruto/Season%201/Episode%2027//27%20The%20Forest%20of%20Death.mp4",
    "fileName": "The Forest of Death.mp4",
    "s3Path": "tv/Naruto (2005)/Season 01/S01E27 - (Ep27) The Forest of Death.mp4",
    "index": 1713
  },
  {
    "title": "Naruto",
    "globalEpisodeNumber": 121,
    "sizeInMB": 82.84,
    "seasonEpisodeNumber": 38,
    "downloadUrl": "https://eng.cartoonsarea.cc/USER-DATA/Cartoonsarea/English/N/Naruto/Season%203/Episode%20121//121%20To%20Each%20His%20Own%20Battle.mp4",
    "fileName": "To Each His Own Battle.mp4",
    "s3Path": "tv/Naruto (2005)/Season 03/S03E38 - (Ep121) To Each His Own Battle.mp4",
    "index": 1714
  },
  {
    "title": "Naruto",
    "globalEpisodeNumber": 136,
    "sizeInMB": 82.84,
    "seasonEpisodeNumber": 5,
    "downloadUrl": "https://eng.cartoonsarea.cc/USER-DATA/Cartoonsarea/English/N/Naruto/Season%204/Episode%20136//136%20Deep%20Cover!%20A%20Super%20S-Ranked%20Mission!.mp4",
    "fileName": "Deep Cover! A Super S-Ranked Mission!.mp4",
    "s3Path": "tv/Naruto (2005)/Season 04/S04E05 - (Ep136) Deep Cover! A Super S-Ranked Mission!.mp4",
    "index": 1715
  },
  {
    "title": "Naruto",
    "globalEpisodeNumber": 15,
    "sizeInMB": 82.85,
    "seasonEpisodeNumber": 15,
    "downloadUrl": "https://eng.cartoonsarea.cc/USER-DATA/Cartoonsarea/English/N/Naruto/Season%201/Episode%2015//15%20Zero%20Visibility,%20The%20Sharingan%20Shatters.mp4",
    "fileName": "Zero Visibility, The Sharingan Shatters.mp4",
    "s3Path": "tv/Naruto (2005)/Season 01/S01E15 - (Ep15) Zero Visibility, The Sharingan Shatters.mp4",
    "index": 1716
  },
  {
    "title": "Naruto",
    "globalEpisodeNumber": 56,
    "sizeInMB": 82.85,
    "seasonEpisodeNumber": 21,
    "downloadUrl": "https://eng.cartoonsarea.cc/USER-DATA/Cartoonsarea/English/N/Naruto/Season%202/Episode%2056//56%20Live%20Or%20Die,%20Risk%20It%20All%20To%20Win%20It%20All!.mp4",
    "fileName": "Live Or Die, Risk It All To Win It All!.mp4",
    "s3Path": "tv/Naruto (2005)/Season 02/S02E21 - (Ep56) Live Or Die, Risk It All To Win It All!.mp4",
    "index": 1717
  },
  {
    "title": "Naruto Shippuden",
    "globalEpisodeNumber": 266,
    "sizeInMB": 82.86,
    "seasonEpisodeNumber": 24,
    "downloadUrl": "https://eng.cartoonsarea.cc/USER-DATA/Cartoonsarea/English/N/Naruto%20Shippuden/Season%2012/Episode%20266//266%20The%20First%20and%20Last%20Opponent.mp4",
    "fileName": "The First and Last Opponent.mp4",
    "s3Path": "tv/Naruto Shippuden (2009)/Season 12/S12E24 - (Ep266) The First and Last Opponent.mp4",
    "index": 1718
  },
  {
    "title": "Naruto Shippuden",
    "globalEpisodeNumber": 329,
    "sizeInMB": 82.86,
    "seasonEpisodeNumber": 9,
    "downloadUrl": "https://eng.cartoonsarea.cc/USER-DATA/Cartoonsarea/English/N/Naruto%20Shippuden/Season%2015/Episode%20329//329%20Two-Man%20Team.mp4",
    "fileName": "Two-Man Team.mp4",
    "s3Path": "tv/Naruto Shippuden (2009)/Season 15/S15E09 - (Ep329) Two-Man Team.mp4",
    "index": 1719
  },
  {
    "title": "Naruto Shippuden",
    "globalEpisodeNumber": 477,
    "sizeInMB": 82.86,
    "seasonEpisodeNumber": 64,
    "downloadUrl": "https://eng.cartoonsarea.cc/USER-DATA/Cartoonsarea/English/N/Naruto%20Shippuden/Season%2020/Episode%20477//477%20Naruto%20and%20Sasuke.mp4",
    "fileName": "Naruto and Sasuke.mp4",
    "s3Path": "tv/Naruto Shippuden (2009)/Season 20/S20E64 - (Ep477) Naruto and Sasuke.mp4",
    "index": 1720
  },
  {
    "title": "Naruto",
    "globalEpisodeNumber": 86,
    "sizeInMB": 82.87,
    "seasonEpisodeNumber": 3,
    "downloadUrl": "https://eng.cartoonsarea.cc/USER-DATA/Cartoonsarea/English/N/Naruto/Season%203/Episode%2086//86%20A%20New%20Training%20Begins,%20I%20Will%20Be%20Strong!.mp4",
    "fileName": "A New Training Begins, I Will Be Strong!.mp4",
    "s3Path": "tv/Naruto (2005)/Season 03/S03E03 - (Ep86) A New Training Begins, I Will Be Strong!.mp4",
    "index": 1721
  },
  {
    "title": "Naruto",
    "globalEpisodeNumber": 115,
    "sizeInMB": 82.87,
    "seasonEpisodeNumber": 32,
    "downloadUrl": "https://eng.cartoonsarea.cc/USER-DATA/Cartoonsarea/English/N/Naruto/Season%203/Episode%20115//115%20Your%20Opponent%20Is%20Me!.mp4",
    "fileName": "Your Opponent Is Me!.mp4",
    "s3Path": "tv/Naruto (2005)/Season 03/S03E32 - (Ep115) Your Opponent Is Me!.mp4",
    "index": 1722
  },
  {
    "title": "Naruto",
    "globalEpisodeNumber": 124,
    "sizeInMB": 82.87,
    "seasonEpisodeNumber": 41,
    "downloadUrl": "https://eng.cartoonsarea.cc/USER-DATA/Cartoonsarea/English/N/Naruto/Season%203/Episode%20124//124%20The%20Beast%20Within.mp4",
    "fileName": "The Beast Within.mp4",
    "s3Path": "tv/Naruto (2005)/Season 03/S03E41 - (Ep124) The Beast Within.mp4",
    "index": 1723
  },
  {
    "title": "Naruto Shippuden",
    "globalEpisodeNumber": 141,
    "sizeInMB": 82.87,
    "seasonEpisodeNumber": 29,
    "downloadUrl": "https://eng.cartoonsarea.cc/USER-DATA/Cartoonsarea/English/N/Naruto%20Shippuden/Season%206/Episode%20141//141%20Truth.mp4",
    "fileName": "Truth.mp4",
    "s3Path": "tv/Naruto Shippuden (2009)/Season 06/S06E29 - (Ep141) Truth.mp4",
    "index": 1724
  },
  {
    "title": "Naruto Shippuden",
    "globalEpisodeNumber": 443,
    "sizeInMB": 82.87,
    "seasonEpisodeNumber": 30,
    "downloadUrl": "https://eng.cartoonsarea.cc/USER-DATA/Cartoonsarea/English/N/Naruto%20Shippuden/Season%2020/Episode%20443//443%20The%20Difference%20in%20Power.mp4",
    "fileName": "The Difference in Power.mp4",
    "s3Path": "tv/Naruto Shippuden (2009)/Season 20/S20E30 - (Ep443) The Difference in Power.mp4",
    "index": 1725
  },
  {
    "title": "Naruto",
    "globalEpisodeNumber": 109,
    "sizeInMB": 82.88,
    "seasonEpisodeNumber": 26,
    "downloadUrl": "https://eng.cartoonsarea.cc/USER-DATA/Cartoonsarea/English/N/Naruto/Season%203/Episode%20109//109%20An%20Invitation%20From%20The%20Sound.mp4",
    "fileName": "An Invitation From The Sound.mp4",
    "s3Path": "tv/Naruto (2005)/Season 03/S03E26 - (Ep109) An Invitation From The Sound.mp4",
    "index": 1726
  },
  {
    "title": "The Legend of Korra",
    "globalEpisodeNumber": 15,
    "sizeInMB": 82.89,
    "seasonEpisodeNumber": 3,
    "downloadUrl": "https://eng.cartoonsarea.cc/USER-DATA/Cartoonsarea/English/A/Avatar%20The%20Legend%20of%20Korra/Season%202%20Spirits/Episode%2015//15%20Civil%20Wars,%20Part%201.mp4",
    "fileName": "Civil Wars, Part 1.mp4",
    "s3Path": "tv/The Legend of Korra (2012)/Season 02/S02E03 - (Ep15) Civil Wars, Part 1.mp4",
    "index": 1727
  },
  {
    "title": "Naruto Shippuden",
    "globalEpisodeNumber": 325,
    "sizeInMB": 82.89,
    "seasonEpisodeNumber": 5,
    "downloadUrl": "https://eng.cartoonsarea.cc/USER-DATA/Cartoonsarea/English/N/Naruto%20Shippuden/Season%2015/Episode%20325//325%20Jinch%C5%ABriki%20vs.%20Jinch%C5%ABriki!!.mp4",
    "fileName": "Jinchūriki vs. Jinchūriki!!.mp4",
    "s3Path": "tv/Naruto Shippuden (2009)/Season 15/S15E05 - (Ep325) Jinchūriki vs. Jinchūriki!!.mp4",
    "index": 1728
  },
  {
    "title": "One-Punch Man",
    "globalEpisodeNumber": 18,
    "sizeInMB": 82.9,
    "seasonEpisodeNumber": 6,
    "downloadUrl": "https://eng.cartoonsarea.cc/USER-DATA/Cartoonsarea/English/O/One%20Punch%20Man/Season%202/Episode%2018//18%20The%20Monster%20Uprising.mp4",
    "fileName": "The Monster Uprising.mp4",
    "s3Path": "tv/One-Punch Man (2015)/Season 02/S02E06 - (Ep18) The Monster Uprising.mp4",
    "index": 1729
  },
  {
    "title": "Naruto",
    "globalEpisodeNumber": 6,
    "sizeInMB": 82.9,
    "seasonEpisodeNumber": 6,
    "downloadUrl": "https://eng.cartoonsarea.cc/USER-DATA/Cartoonsarea/English/N/Naruto/Season%201/Episode%206//06%20Journey%20to%20the%20Land%20of%20the%20Waves.mp4",
    "fileName": "Journey to the Land of the Waves.mp4",
    "s3Path": "tv/Naruto (2005)/Season 01/S01E06 - (Ep06) Journey to the Land of the Waves.mp4",
    "index": 1730
  },
  {
    "title": "Naruto",
    "globalEpisodeNumber": 52,
    "sizeInMB": 82.9,
    "seasonEpisodeNumber": 17,
    "downloadUrl": "https://eng.cartoonsarea.cc/USER-DATA/Cartoonsarea/English/N/Naruto/Season%202/Episode%2052//52%20Ebisu%20Returns,%20Naruto's%20Toughest%20Training%20Yet!.mp4",
    "fileName": "Ebisu Returns, Naruto's Toughest Training Yet!.mp4",
    "s3Path": "tv/Naruto (2005)/Season 02/S02E17 - (Ep52) Ebisu Returns, Naruto's Toughest Training Yet!.mp4",
    "index": 1731
  },
  {
    "title": "Naruto",
    "globalEpisodeNumber": 162,
    "sizeInMB": 82.9,
    "seasonEpisodeNumber": 31,
    "downloadUrl": "https://eng.cartoonsarea.cc/USER-DATA/Cartoonsarea/English/N/Naruto/Season%204/Episode%20162//162%20The%20Cursed%20Warrior.mp4",
    "fileName": "The Cursed Warrior.mp4",
    "s3Path": "tv/Naruto (2005)/Season 04/S04E31 - (Ep162) The Cursed Warrior.mp4",
    "index": 1732
  },
  {
    "title": "Naruto",
    "globalEpisodeNumber": 209,
    "sizeInMB": 82.9,
    "seasonEpisodeNumber": 24,
    "downloadUrl": "https://eng.cartoonsarea.cc/USER-DATA/Cartoonsarea/English/N/Naruto/Season%205/Episode%20209//209%20The%20Enemy,%20Ninja%20Dropouts.mp4",
    "fileName": "The Enemy, Ninja Dropouts.mp4",
    "s3Path": "tv/Naruto (2005)/Season 05/S05E24 - (Ep209) The Enemy, Ninja Dropouts.mp4",
    "index": 1733
  },
  {
    "title": "Naruto Shippuden",
    "globalEpisodeNumber": 10,
    "sizeInMB": 82.9,
    "seasonEpisodeNumber": 10,
    "downloadUrl": "https://eng.cartoonsarea.cc/USER-DATA/Cartoonsarea/English/N/Naruto%20Shippuden/Season%201/Episode%2010//10%20Sealing%20Jutsu%20Nine%20Phantom%20Dragons.mp4",
    "fileName": "Sealing Jutsu Nine Phantom Dragons.mp4",
    "s3Path": "tv/Naruto Shippuden (2009)/Season 01/S01E10 - (Ep10) Sealing Jutsu Nine Phantom Dragons.mp4",
    "index": 1734
  },
  {
    "title": "Naruto Shippuden",
    "globalEpisodeNumber": 200,
    "sizeInMB": 82.9,
    "seasonEpisodeNumber": 4,
    "downloadUrl": "https://eng.cartoonsarea.cc/USER-DATA/Cartoonsarea/English/N/Naruto%20Shippuden/Season%2010/Episode%20200//200%20Naruto's%20Plea.mp4",
    "fileName": "Naruto's Plea.mp4",
    "s3Path": "tv/Naruto Shippuden (2009)/Season 10/S10E04 - (Ep200) Naruto's Plea.mp4",
    "index": 1735
  },
  {
    "title": "Naruto",
    "globalEpisodeNumber": 210,
    "sizeInMB": 82.91,
    "seasonEpisodeNumber": 25,
    "downloadUrl": "https://eng.cartoonsarea.cc/USER-DATA/Cartoonsarea/English/N/Naruto/Season%205/Episode%20210//210%20The%20Bewildering%20Forest.mp4",
    "fileName": "The Bewildering Forest.mp4",
    "s3Path": "tv/Naruto (2005)/Season 05/S05E25 - (Ep210) The Bewildering Forest.mp4",
    "index": 1736
  },
  {
    "title": "Naruto Shippuden",
    "globalEpisodeNumber": 133,
    "sizeInMB": 82.91,
    "seasonEpisodeNumber": 21,
    "downloadUrl": "https://eng.cartoonsarea.cc/USER-DATA/Cartoonsarea/English/N/Naruto%20Shippuden/Season%206/Episode%20133//133%20The%20Tale%20of%20Jiraiya%20the%20Gallant.mp4",
    "fileName": "The Tale of Jiraiya the Gallant.mp4",
    "s3Path": "tv/Naruto Shippuden (2009)/Season 06/S06E21 - (Ep133) The Tale of Jiraiya the Gallant.mp4",
    "index": 1737
  },
  {
    "title": "Naruto",
    "globalEpisodeNumber": 127,
    "sizeInMB": 82.92,
    "seasonEpisodeNumber": 44,
    "downloadUrl": "https://eng.cartoonsarea.cc/USER-DATA/Cartoonsarea/English/N/Naruto/Season%203/Episode%20127//127%20Vengeful%20Strike!%20The%20Bracken%20Dance!.mp4",
    "fileName": "Vengeful Strike! The Bracken Dance!.mp4",
    "s3Path": "tv/Naruto (2005)/Season 03/S03E44 - (Ep127) Vengeful Strike! The Bracken Dance!.mp4",
    "index": 1738
  },
  {
    "title": "Naruto Shippuden",
    "globalEpisodeNumber": 419,
    "sizeInMB": 82.92,
    "seasonEpisodeNumber": 6,
    "downloadUrl": "https://eng.cartoonsarea.cc/USER-DATA/Cartoonsarea/English/N/Naruto%20Shippuden/Season%2020/Episode%20419//419%20Papa's%20Youth.mp4",
    "fileName": "Papa's Youth.mp4",
    "s3Path": "tv/Naruto Shippuden (2009)/Season 20/S20E06 - (Ep419) Papa's Youth.mp4",
    "index": 1739
  },
  {
    "title": "Naruto",
    "globalEpisodeNumber": 59,
    "sizeInMB": 82.93,
    "seasonEpisodeNumber": 24,
    "downloadUrl": "https://eng.cartoonsarea.cc/USER-DATA/Cartoonsarea/English/N/Naruto/Season%202/Episode%2059//59%20The%20Final%20Rounds,%20Rush%20To%20The%20Battle%20Arena!.mp4",
    "fileName": "The Final Rounds, Rush To The Battle Arena!.mp4",
    "s3Path": "tv/Naruto (2005)/Season 02/S02E24 - (Ep59) The Final Rounds, Rush To The Battle Arena!.mp4",
    "index": 1740
  },
  {
    "title": "Naruto",
    "globalEpisodeNumber": 61,
    "sizeInMB": 82.93,
    "seasonEpisodeNumber": 26,
    "downloadUrl": "https://eng.cartoonsarea.cc/USER-DATA/Cartoonsarea/English/N/Naruto/Season%202/Episode%2061//61%20Ultimate%20Defense,%20Zero%20Blind%20Spot!.mp4",
    "fileName": "Ultimate Defense, Zero Blind Spot!.mp4",
    "s3Path": "tv/Naruto (2005)/Season 02/S02E26 - (Ep61) Ultimate Defense, Zero Blind Spot!.mp4",
    "index": 1741
  },
  {
    "title": "Naruto",
    "globalEpisodeNumber": 81,
    "sizeInMB": 82.93,
    "seasonEpisodeNumber": 46,
    "downloadUrl": "https://eng.cartoonsarea.cc/USER-DATA/Cartoonsarea/English/N/Naruto/Season%202/Episode%2080//80%20The%20Third%20Hokage,%20Forever...mp4",
    "fileName": "The Third Hokage, Forever...mp4",
    "s3Path": "tv/Naruto (2005)/Season 02/S02E46 - (Ep81) The Third Hokage, Forever...mp4",
    "index": 1742
  },
  {
    "title": "Naruto Shippuden",
    "globalEpisodeNumber": 313,
    "sizeInMB": 82.93,
    "seasonEpisodeNumber": 18,
    "downloadUrl": "https://eng.cartoonsarea.cc/USER-DATA/Cartoonsarea/English/N/Naruto%20Shippuden/Season%2014/Episode%20313//313%20Rain%20Followed%20by%20Snow,%20with%20Some%20Lightning.mp4",
    "fileName": "Rain Followed by Snow, with Some Lightning.mp4",
    "s3Path": "tv/Naruto Shippuden (2009)/Season 14/S14E18 - (Ep313) Rain Followed by Snow, with Some Lightning.mp4",
    "index": 1743
  },
  {
    "title": "Naruto Shippuden",
    "globalEpisodeNumber": 449,
    "sizeInMB": 82.93,
    "seasonEpisodeNumber": 36,
    "downloadUrl": "https://eng.cartoonsarea.cc/USER-DATA/Cartoonsarea/English/N/Naruto%20Shippuden/Season%2020/Episode%20449//449%20The%20Shinobi%20Unite.mp4",
    "fileName": "The Shinobi Unite.mp4",
    "s3Path": "tv/Naruto Shippuden (2009)/Season 20/S20E36 - (Ep449) The Shinobi Unite.mp4",
    "index": 1744
  },
  {
    "title": "Naruto",
    "globalEpisodeNumber": 54,
    "sizeInMB": 82.95,
    "seasonEpisodeNumber": 19,
    "downloadUrl": "https://eng.cartoonsarea.cc/USER-DATA/Cartoonsarea/English/N/Naruto/Season%202/Episode%2054//54%20The%20Summoning%20Jutsu,%20Wisdom%20Of%20The%20Toad%20Sage!.mp4",
    "fileName": "The Summoning Jutsu, Wisdom Of The Toad Sage!.mp4",
    "s3Path": "tv/Naruto (2005)/Season 02/S02E19 - (Ep54) The Summoning Jutsu, Wisdom Of The Toad Sage!.mp4",
    "index": 1745
  },
  {
    "title": "The Legend of Korra",
    "globalEpisodeNumber": 19,
    "sizeInMB": 82.98,
    "seasonEpisodeNumber": 7,
    "downloadUrl": "https://eng.cartoonsarea.cc/USER-DATA/Cartoonsarea/English/A/Avatar%20The%20Legend%20of%20Korra/Season%202%20Spirits/Episode%2019//19%20Beginnings,%20Part%201.mp4",
    "fileName": "Beginnings, Part 1.mp4",
    "s3Path": "tv/The Legend of Korra (2012)/Season 02/S02E07 - (Ep19) Beginnings, Part 1.mp4",
    "index": 1746
  },
  {
    "title": "Naruto",
    "globalEpisodeNumber": 40,
    "sizeInMB": 82.98,
    "seasonEpisodeNumber": 5,
    "downloadUrl": "https://eng.cartoonsarea.cc/USER-DATA/Cartoonsarea/English/N/Naruto/Season%202/Episode%2040//40%20Kakashi%20And%20Orochimaru,%20Face-To-Face!.mp4",
    "fileName": "Kakashi And Orochimaru, Face-To-Face!.mp4",
    "s3Path": "tv/Naruto (2005)/Season 02/S02E05 - (Ep40) Kakashi And Orochimaru, Face-To-Face!.mp4",
    "index": 1747
  },
  {
    "title": "Naruto",
    "globalEpisodeNumber": 55,
    "sizeInMB": 82.98,
    "seasonEpisodeNumber": 20,
    "downloadUrl": "https://eng.cartoonsarea.cc/USER-DATA/Cartoonsarea/English/N/Naruto/Season%202/Episode%2055//55%20A%20Feeling%20Of%20Yearning,%20A%20Flower%20Full%20Of%20Hope.mp4",
    "fileName": "A Feeling Of Yearning, A Flower Full Of Hope.mp4",
    "s3Path": "tv/Naruto (2005)/Season 02/S02E20 - (Ep55) A Feeling Of Yearning, A Flower Full Of Hope.mp4",
    "index": 1748
  },
  {
    "title": "Naruto",
    "globalEpisodeNumber": 72,
    "sizeInMB": 82.98,
    "seasonEpisodeNumber": 37,
    "downloadUrl": "https://eng.cartoonsarea.cc/USER-DATA/Cartoonsarea/English/N/Naruto/Season%202/Episode%2081//81%20Return%20Of%20The%20Morning%20Mist.mp4",
    "fileName": "Return Of The Morning Mist.mp4",
    "s3Path": "tv/Naruto (2005)/Season 02/S02E37 - (Ep72) Return Of The Morning Mist.mp4",
    "index": 1749
  },
  {
    "title": "Naruto",
    "globalEpisodeNumber": 131,
    "sizeInMB": 82.98,
    "seasonEpisodeNumber": 48,
    "downloadUrl": "https://eng.cartoonsarea.cc/USER-DATA/Cartoonsarea/English/N/Naruto/Season%203/Episode%20131//131%20The%20Secrets%20Of%20The%20Mangekyo%20Sharingan.mp4",
    "fileName": "The Secrets Of The Mangekyo Sharingan.mp4",
    "s3Path": "tv/Naruto (2005)/Season 03/S03E48 - (Ep131) The Secrets Of The Mangekyo Sharingan.mp4",
    "index": 1750
  },
  {
    "title": "Naruto Shippuden",
    "globalEpisodeNumber": 315,
    "sizeInMB": 82.98,
    "seasonEpisodeNumber": 20,
    "downloadUrl": "https://eng.cartoonsarea.cc/USER-DATA/Cartoonsarea/English/N/Naruto%20Shippuden/Season%2014/Episode%20315//315%20Lingering%20Snow.mp4",
    "fileName": "Lingering Snow.mp4",
    "s3Path": "tv/Naruto Shippuden (2009)/Season 14/S14E20 - (Ep315) Lingering Snow.mp4",
    "index": 1751
  },
  {
    "title": "Naruto Shippuden",
    "globalEpisodeNumber": 114,
    "sizeInMB": 82.99,
    "seasonEpisodeNumber": 2,
    "downloadUrl": "https://eng.cartoonsarea.cc/USER-DATA/Cartoonsarea/English/N/Naruto%20Shippuden/Season%206/Episode%20114//114%20Eye%20of%20the%20Hawk.mp4",
    "fileName": "Eye of the Hawk.mp4",
    "s3Path": "tv/Naruto Shippuden (2009)/Season 06/S06E02 - (Ep114) Eye of the Hawk.mp4",
    "index": 1752
  },
  {
    "title": "Naruto Shippuden",
    "globalEpisodeNumber": 165,
    "sizeInMB": 82.99,
    "seasonEpisodeNumber": 14,
    "downloadUrl": "https://eng.cartoonsarea.cc/USER-DATA/Cartoonsarea/English/N/Naruto%20Shippuden/Season%208/Episode%20165//165%20Nine-Tails,%20Captured!.mp4",
    "fileName": "Nine-Tails, Captured!.mp4",
    "s3Path": "tv/Naruto Shippuden (2009)/Season 08/S08E14 - (Ep165) Nine-Tails, Captured!.mp4",
    "index": 1753
  },
  {
    "title": "Naruto",
    "globalEpisodeNumber": 10,
    "sizeInMB": 83,
    "seasonEpisodeNumber": 10,
    "downloadUrl": "https://eng.cartoonsarea.cc/USER-DATA/Cartoonsarea/English/N/Naruto/Season%201/Episode%2010//10%20The%20Forest%20of%20Chakra.mp4",
    "fileName": "The Forest of Chakra.mp4",
    "s3Path": "tv/Naruto (2005)/Season 01/S01E10 - (Ep10) The Forest of Chakra.mp4",
    "index": 1754
  },
  {
    "title": "Naruto",
    "globalEpisodeNumber": 122,
    "sizeInMB": 83,
    "seasonEpisodeNumber": 39,
    "downloadUrl": "https://eng.cartoonsarea.cc/USER-DATA/Cartoonsarea/English/N/Naruto/Season%203/Episode%20122//122%20Fakeout,%20Shikamaru's%20Comeback!.mp4",
    "fileName": "Fakeout, Shikamaru's Comeback!.mp4",
    "s3Path": "tv/Naruto (2005)/Season 03/S03E39 - (Ep122) Fakeout, Shikamaru's Comeback!.mp4",
    "index": 1755
  },
  {
    "title": "Naruto",
    "globalEpisodeNumber": 174,
    "sizeInMB": 83.01,
    "seasonEpisodeNumber": 43,
    "downloadUrl": "https://eng.cartoonsarea.cc/USER-DATA/Cartoonsarea/English/N/Naruto/Season%204/Episode%20174//174%20Impossible!%20Celebrity%20Ninja%20Art,%20Money%20Style%20Jutsu!.mp4",
    "fileName": "Impossible! Celebrity Ninja Art, Money Style Jutsu!.mp4",
    "s3Path": "tv/Naruto (2005)/Season 04/S04E43 - (Ep174) Impossible! Celebrity Ninja Art, Money Style Jutsu!.mp4",
    "index": 1756
  },
  {
    "title": "Naruto",
    "globalEpisodeNumber": 42,
    "sizeInMB": 83.02,
    "seasonEpisodeNumber": 7,
    "downloadUrl": "https://eng.cartoonsarea.cc/USER-DATA/Cartoonsarea/English/N/Naruto/Season%202/Episode%2042//42%20The%20Ultimate%20Battle,%20Cha!.mp4",
    "fileName": "The Ultimate Battle, Cha!.mp4",
    "s3Path": "tv/Naruto (2005)/Season 02/S02E07 - (Ep42) The Ultimate Battle, Cha!.mp4",
    "index": 1757
  },
  {
    "title": "Avatar: The Last Airbender",
    "globalEpisodeNumber": 24,
    "sizeInMB": 83.03,
    "seasonEpisodeNumber": 4,
    "downloadUrl": "https://eng.cartoonsarea.cc/USER-DATA/Cartoonsarea/English/A/Avatar%20The%20Last%20Airbender/Season%202%20Earth/Episode%2024//24%20The%20Swamp.mp4",
    "fileName": "The Swamp.mp4",
    "s3Path": "tv/Avatar: The Last Airbender (2005)/Season 02/S02E04 - (Ep24) The Swamp.mp4",
    "index": 1758
  },
  {
    "title": "Naruto",
    "globalEpisodeNumber": 53,
    "sizeInMB": 83.03,
    "seasonEpisodeNumber": 18,
    "downloadUrl": "https://eng.cartoonsarea.cc/USER-DATA/Cartoonsarea/English/N/Naruto/Season%202/Episode%2053//53%20Long%20Time%20No%20See,%20Jiraya%20Returns!.mp4",
    "fileName": "Long Time No See, Jiraya Returns!.mp4",
    "s3Path": "tv/Naruto (2005)/Season 02/S02E18 - (Ep53) Long Time No See, Jiraya Returns!.mp4",
    "index": 1759
  },
  {
    "title": "Naruto",
    "globalEpisodeNumber": 111,
    "sizeInMB": 83.03,
    "seasonEpisodeNumber": 28,
    "downloadUrl": "https://eng.cartoonsarea.cc/USER-DATA/Cartoonsarea/English/N/Naruto/Season%203/Episode%20111//111%20Sound%20vs.%20Leaf.mp4",
    "fileName": "Sound vs. Leaf.mp4",
    "s3Path": "tv/Naruto (2005)/Season 03/S03E28 - (Ep111) Sound vs. Leaf.mp4",
    "index": 1760
  },
  {
    "title": "Naruto Shippuden",
    "globalEpisodeNumber": 112,
    "sizeInMB": 83.03,
    "seasonEpisodeNumber": 24,
    "downloadUrl": "https://eng.cartoonsarea.cc/USER-DATA/Cartoonsarea/English/N/Naruto%20Shippuden/Season%205/Episode%20112//112%20A%20Place%20to%20Return%20To.mp4",
    "fileName": "A Place to Return To.mp4",
    "s3Path": "tv/Naruto Shippuden (2009)/Season 05/S05E24 - (Ep112) A Place to Return To.mp4",
    "index": 1761
  },
  {
    "title": "Naruto",
    "globalEpisodeNumber": 20,
    "sizeInMB": 83.04,
    "seasonEpisodeNumber": 20,
    "downloadUrl": "https://eng.cartoonsarea.cc/USER-DATA/Cartoonsarea/English/N/Naruto/Season%201/Episode%2020//20%20A%20New%20Chapter%20Begins,%20The%20Chuunin%20Exam.mp4",
    "fileName": "A New Chapter Begins, The Chuunin Exam.mp4",
    "s3Path": "tv/Naruto (2005)/Season 01/S01E20 - (Ep20) A New Chapter Begins, The Chuunin Exam.mp4",
    "index": 1762
  },
  {
    "title": "Naruto",
    "globalEpisodeNumber": 176,
    "sizeInMB": 83.04,
    "seasonEpisodeNumber": 45,
    "downloadUrl": "https://eng.cartoonsarea.cc/USER-DATA/Cartoonsarea/English/N/Naruto/Season%204/Episode%20176//176%20Run,%20Dodge,%20Zigzag!%20Chase%20Or%20Be%20Chased!.mp4",
    "fileName": "Run, Dodge, Zigzag! Chase Or Be Chased!.mp4",
    "s3Path": "tv/Naruto (2005)/Season 04/S04E45 - (Ep176) Run, Dodge, Zigzag! Chase Or Be Chased!.mp4",
    "index": 1763
  },
  {
    "title": "Pokémon",
    "globalEpisodeNumber": 61,
    "sizeInMB": 83.05,
    "seasonEpisodeNumber": 61,
    "downloadUrl": "https://eng.cartoonsarea.cc/USER-DATA/Cartoonsarea/English/P/Pokemon/Season%201/Episode%2061//61%20The%20Misty%20Mermaid.mp4",
    "fileName": "The Misty Mermaid.mp4",
    "s3Path": "tv/Pokémon (1997)/Season 01/S01E61 - (Ep61) The Misty Mermaid.mp4",
    "index": 1764
  },
  {
    "title": "Pokémon",
    "globalEpisodeNumber": 63,
    "sizeInMB": 83.05,
    "seasonEpisodeNumber": 63,
    "downloadUrl": "https://eng.cartoonsarea.cc/USER-DATA/Cartoonsarea/English/P/Pokemon/Season%201/Episode%2063//63%20The%20Battle%20of%20the%20Badge.mp4",
    "fileName": "The Battle of the Badge.mp4",
    "s3Path": "tv/Pokémon (1997)/Season 01/S01E63 - (Ep63) The Battle of the Badge.mp4",
    "index": 1765
  },
  {
    "title": "Naruto",
    "globalEpisodeNumber": 4,
    "sizeInMB": 83.06,
    "seasonEpisodeNumber": 4,
    "downloadUrl": "https://eng.cartoonsarea.cc/USER-DATA/Cartoonsarea/English/N/Naruto/Season%201/Episode%204//04%20Pass%20or%20Fail%20Survival%20Test.mp4",
    "fileName": "Pass or Fail Survival Test.mp4",
    "s3Path": "tv/Naruto (2005)/Season 01/S01E04 - (Ep04) Pass or Fail Survival Test.mp4",
    "index": 1766
  },
  {
    "title": "Naruto",
    "globalEpisodeNumber": 116,
    "sizeInMB": 83.06,
    "seasonEpisodeNumber": 33,
    "downloadUrl": "https://eng.cartoonsarea.cc/USER-DATA/Cartoonsarea/English/N/Naruto/Season%203/Episode%20116//116%20360%20Degrees%20Of%20Vision,%20The%20Byakugan's%20Blind%20Spot.mp4",
    "fileName": "360 Degrees Of Vision, The Byakugan's Blind Spot.mp4",
    "s3Path": "tv/Naruto (2005)/Season 03/S03E33 - (Ep116) 360 Degrees Of Vision, The Byakugan's Blind Spot.mp4",
    "index": 1767
  },
  {
    "title": "Naruto",
    "globalEpisodeNumber": 125,
    "sizeInMB": 83.06,
    "seasonEpisodeNumber": 42,
    "downloadUrl": "https://eng.cartoonsarea.cc/USER-DATA/Cartoonsarea/English/N/Naruto/Season%203/Episode%20125//125%20The%20Sand%20Shinobi,%20Allies%20Of%20The%20Leaf.mp4",
    "fileName": "The Sand Shinobi, Allies Of The Leaf.mp4",
    "s3Path": "tv/Naruto (2005)/Season 03/S03E42 - (Ep125) The Sand Shinobi, Allies Of The Leaf.mp4",
    "index": 1768
  },
  {
    "title": "Naruto",
    "globalEpisodeNumber": 211,
    "sizeInMB": 83.06,
    "seasonEpisodeNumber": 26,
    "downloadUrl": "https://eng.cartoonsarea.cc/USER-DATA/Cartoonsarea/English/N/Naruto/Season%205/Episode%20211//211%20Memory%20Of%20Flames.mp4",
    "fileName": "Memory Of Flames.mp4",
    "s3Path": "tv/Naruto (2005)/Season 05/S05E26 - (Ep211) Memory Of Flames.mp4",
    "index": 1769
  },
  {
    "title": "Martin Mystery",
    "globalEpisodeNumber": 62,
    "sizeInMB": 83.08,
    "seasonEpisodeNumber": 22,
    "downloadUrl": "https://eng.cartoonsarea.cc/USER-DATA/Cartoonsarea/English/M/Martin%20Mystery/Seasons%203/Episode%2062//62%20Wrath%20Of%20The%20Venus%20Flytrap.mp4",
    "fileName": "Wrath Of The Venus Flytrap.mp4",
    "s3Path": "tv/Martin Mystery (2003)/Season 03/S03E22 - (Ep62) Wrath Of The Venus Flytrap.mp4",
    "index": 1770
  },
  {
    "title": "Naruto",
    "globalEpisodeNumber": 34,
    "sizeInMB": 83.08,
    "seasonEpisodeNumber": 34,
    "downloadUrl": "https://eng.cartoonsarea.cc/USER-DATA/Cartoonsarea/English/N/Naruto/Season%201/Episode%2034//34%20Akamaru%20Trembles%20Gaara's%20Cruel%20Strength.mp4",
    "fileName": "Akamaru Trembles Gaara's Cruel Strength.mp4",
    "s3Path": "tv/Naruto (2005)/Season 01/S01E34 - (Ep34) Akamaru Trembles Gaara's Cruel Strength.mp4",
    "index": 1771
  },
  {
    "title": "Naruto",
    "globalEpisodeNumber": 206,
    "sizeInMB": 83.08,
    "seasonEpisodeNumber": 21,
    "downloadUrl": "https://eng.cartoonsarea.cc/USER-DATA/Cartoonsarea/English/N/Naruto/Season%205/Episode%20206//206%20Genjutsu%20Or%20Reality.mp4",
    "fileName": "Genjutsu Or Reality.mp4",
    "s3Path": "tv/Naruto (2005)/Season 05/S05E21 - (Ep206) Genjutsu Or Reality.mp4",
    "index": 1772
  }
]